ldraw_to_scad/__init__.py
ldraw_to_scad/ldrawconverter.py
ldraw_to_scad/lib.scad
ldraw_to_scad-0.5.0.data/scripts/ldraw2scad
ldraw_to_scad-0.5.0.dist-info/licenses/LICENSE
ldraw_to_scad-0.5.0.dist-info/METADATA
ldraw_to_scad-0.5.0.dist-info/WHEEL
ldraw_to_scad-0.5.0.dist-info/top_level.txt
ldraw_to_scad-0.5.0.dist-info/RECORD
