Metadata-Version: 2.4
Name: ldraw-to-scad
Version: 0.5.0
Summary: The LDraw to OpenSCAD converter library
Home-page: https://github.com/orionrobots/ldraw-to-scad
Author: Danny Staple
Author-email: danny@orionrobots.co.uk
Maintainer: Robert Schiele
Maintainer-email: rschiele@gmail.com
Project-URL: Bug Tracker, https://github.com/orionrobots/ldraw-to-scad/issues
Classifier: Programming Language :: Python :: 3
Classifier: License :: OSI Approved :: Apache Software License
Classifier: Operating System :: OS Independent
Requires-Python: >=3.6
License-File: LICENSE
Dynamic: license-file
